README.md
setup.py
conda_docker/__init__.py
conda_docker/__main__.py
conda_docker/cli.py
conda_docker/conda.py
conda_docker/logging.py
conda_docker/utils.py
conda_docker.egg-info/PKG-INFO
conda_docker.egg-info/SOURCES.txt
conda_docker.egg-info/dependency_links.txt
conda_docker.egg-info/entry_points.txt
conda_docker.egg-info/not-zip-safe
conda_docker.egg-info/top_level.txt
conda_docker/docker/base.py
conda_docker/docker/client.py
conda_docker/docker/tar.py
conda_docker/registry/api.py
conda_docker/registry/client.py