Metadata-Version: 2.1
Name: conda-docker
Version: 0.0.1
Summary: Create minimal docker images from conda environments
Home-page: https://github.com/regro/conda-docker
Author: conda-forge
Author-email: conda-forge@googlegroups.com
Maintainer: conda-forge
License: BSD-3-Clause
Platform: Cross Platform
Classifier: Programming Language :: Python :: 3
Requires-Python: >=3.6
